wiki_displayer/wiki.py
random_wikipedia_article_yuhan-0.1.2.dist-info/METADATA
random_wikipedia_article_yuhan-0.1.2.dist-info/WHEEL
random_wikipedia_article_yuhan-0.1.2.dist-info/entry_points.txt
random_wikipedia_article_yuhan-0.1.2.dist-info/RECORD
